paradise/__init__.py
paradise/rpplayer.py
paradise_player/__init__.py
paradise_player/rpplayer.py
paradise_player-0.2.dist-info/METADATA
paradise_player-0.2.dist-info/RECORD
paradise_player-0.2.dist-info/WHEEL
paradise_player-0.2.dist-info/entry_points.txt
paradise_player-0.2.dist-info/top_level.txt
