Metadata-Version: 2.1
Name: paradise-player
Version: 0.2
Summary: CLI Player and notifier for radio paradise
Home-page: UNKNOWN
Author: Thomas Chiroux
Author-email: 
License: LICENSE
Keywords: radio_paradise radio player notification
Platform: UNKNOWN
Classifier: License :: OSI Approved :: MIT License
Classifier: Programming Language :: Python
Classifier: Programming Language :: Python :: 3.4
Classifier: Programming Language :: Python :: 3.5
Classifier: Programming Language :: Python :: 3.6
Classifier: Programming Language :: Python :: 3.7
Classifier: Operating System :: POSIX :: Linux
Requires-Dist: requests
